caramel_client-1.5.0.data/scripts/caramel-client
caramelrequest/__init__.py
caramelrequest/certificaterequest.py
caramel_client-1.5.0.dist-info/LICENSE
caramel_client-1.5.0.dist-info/METADATA
caramel_client-1.5.0.dist-info/WHEEL
caramel_client-1.5.0.dist-info/top_level.txt
caramel_client-1.5.0.dist-info/zip-safe
caramel_client-1.5.0.dist-info/RECORD
