Metadata-Version: 2.1
Name: caramel-client
Version: 1.5.0
Summary: caramel-client: A python client for the Caramel CA system.
Home-page: https://github.com/ModioAB/caramel-client
Author: D.S. Ljungmark
Author-email: spider@modio.se
License: UNKNOWN
Download-URL: https://github.com/ModioAB/caramel-client/releases/tag/1.5.0
Keywords: caramel ssl tls certificates x509 ca cert
Platform: UNKNOWN
Classifier: Programming Language :: Python
Requires-Dist: requests
